{
  "id": "20ecd82d-4fbf-4978-94ec-1583422850c8",
  "prevId": "00000000-0000-0000-0000-000000000000",
  "version": "7",
  "dialect": "postgresql",
  "tables": {
    "public.activities": {
      "name": "activities",
      "schema": "",
      "columns": {
        "id": {
          "name": "id",
          "type": "uuid",
          "primaryKey": true,
          "notNull": true,
          "default": "gen_random_uuid()"
        },
        "city_id": {
          "name": "city_id",
          "type": "uuid",
          "primaryKey": false,
          "notNull": true
        },
        "name": {
          "name": "name",
          "type": "text",
          "primaryKey": false,
          "notNull": true
        },
        "category": {
          "name": "category",
          "type": "preference_category",
          "typeSchema": "public",
          "primaryKey": false,
          "notNull": true
        },
        "duration_minutes": {
          "name": "duration_minutes",
          "type": "integer",
          "primaryKey": false,
          "notNull": true
        },
        "cost_usd": {
          "name": "cost_usd",
          "type": "real",
          "primaryKey": false,
          "notNull": true
        },
        "address": {
          "name": "address",
          "type": "text",
          "primaryKey": false,
          "notNull": true
        },
        "lat": {
          "name": "lat",
          "type": "real",
          "primaryKey": false,
          "notNull": true
        },
        "lng": {
          "name": "lng",
          "type": "real",
          "primaryKey": false,
          "notNull": true
        }
      },
      "indexes": {
        "activities_city_idx": {
          "name": "activities_city_idx",
          "columns": [
            {
              "expression": "city_id",
              "isExpression": false,
              "asc": true,
              "nulls": "last"
            }
          ],
          "isUnique": false,
          "concurrently": false,
          "method": "btree",
          "with": {}
        },
        "activities_city_name_idx": {
          "name": "activities_city_name_idx",
          "columns": [
            {
              "expression": "city_id",
              "isExpression": false,
              "asc": true,
              "nulls": "last"
            },
            {
              "expression": "name",
              "isExpression": false,
              "asc": true,
              "nulls": "last"
            }
          ],
          "isUnique": true,
          "concurrently": false,
          "method": "btree",
          "with": {}
        }
      },
      "foreignKeys": {
        "activities_city_id_cities_id_fk": {
          "name": "activities_city_id_cities_id_fk",
          "tableFrom": "activities",
          "tableTo": "cities",
          "columnsFrom": [
            "city_id"
          ],
          "columnsTo": [
            "id"
          ],
          "onDelete": "cascade",
          "onUpdate": "no action"
        }
      },
      "compositePrimaryKeys": {},
      "uniqueConstraints": {},
      "policies": {},
      "checkConstraints": {},
      "isRLSEnabled": false
    },
    "public.cities": {
      "name": "cities",
      "schema": "",
      "columns": {
        "id": {
          "name": "id",
          "type": "uuid",
          "primaryKey": true,
          "notNull": true,
          "default": "gen_random_uuid()"
        },
        "key": {
          "name": "key",
          "type": "text",
          "primaryKey": false,
          "notNull": true
        },
        "display_name": {
          "name": "display_name",
          "type": "text",
          "primaryKey": false,
          "notNull": true
        },
        "country": {
          "name": "country",
          "type": "text",
          "primaryKey": false,
          "notNull": true
        }
      },
      "indexes": {},
      "foreignKeys": {},
      "compositePrimaryKeys": {},
      "uniqueConstraints": {
        "cities_key_unique": {
          "name": "cities_key_unique",
          "nullsNotDistinct": false,
          "columns": [
            "key"
          ]
        }
      },
      "policies": {},
      "checkConstraints": {},
      "isRLSEnabled": false
    }
  },
  "enums": {
    "public.preference_category": {
      "name": "preference_category",
      "schema": "public",
      "values": [
        "food",
        "culture",
        "outdoor",
        "nightlife",
        "shopping"
      ]
    }
  },
  "schemas": {},
  "sequences": {},
  "roles": {},
  "policies": {},
  "views": {},
  "_meta": {
    "columns": {},
    "schemas": {},
    "tables": {}
  }
}